cunnypy/__init__.py
cunnypy/autocomplete.py
cunnypy/boorus.py
cunnypy/errors.py
cunnypy/py.typed
cunnypy/search.py
cunnypy/utils.py
cunnypy-3.0.0.dist-info/LICENSE
cunnypy-3.0.0.dist-info/METADATA
cunnypy-3.0.0.dist-info/WHEEL
cunnypy-3.0.0.dist-info/RECORD
